<?xml version="1.0" encoding="UTF-8"?>
<templates id="template" xml:space="preserve">

    <!--Replace the create button on a picking listview to have 'Planned Transfer' functionality instead of 'Immediate Transfer'-->
    <t t-extend="ListView.buttons">
        <t t-jquery="button.o_list_button_add" t-operation="replace">
            <t t-if="widget.modelName=='stock.picking'">
                <button class="btn btn-primary btn-sm o_list_button_add_planned" type="button">Create</button>
            </t>
            <t t-else="">
                <button class="btn btn-primary btn-sm o_list_button_add" type="button">Create</button>
            </t>
        </t>
    </t>

    <!--Replace the create button on a picking formview to have 'Planned Transfer' functionality instead of 'Immediate Transfer'-->
    <t t-extend="FormView.buttons">
        <t t-jquery="button.o_form_button_create" t-operation="replace">
            <t t-if="widget.modelName=='stock.picking'">
                <button class="btn btn-primary btn-sm o_form_button_add_planned" type="button">Create</button>
            </t>
            <t t-else="">
                <button class="btn btn-primary btn-sm o_form_button_create" type="button">Create</button>
            </t>
        </t>
    </t>

    <!--Replace the create button on a picking kanban view to have 'Planned Transfer' functionality instead of 'Immediate Transfer'-->
    <t t-extend="KanbanView.buttons">
        <t t-jquery="button.o-kanban-button-new" t-operation="replace">
            <t t-if="widget.modelName=='stock.picking'">
                <button class="btn btn-primary btn-sm o_list_button_add_planned" type="button">Create</button>
            </t>
            <t t-else="">
                <button class="btn btn-primary btn-sm o-kanban-button-new" type="button">Create</button>
            </t>
        </t>
    </t>

    <!--Reposition the Import button when the Create button has been replaced on a picking listview-->
    <t t-extend="ListView.buttons">
        <t t-if="widget.modelName=='stock.picking'" t-jquery="button.o_list_button_add_planned" t-operation="after">
           <t t-call="ImportView.import_button"/>
        </t>
    </t>

    <!--Reposition the Import button when the Create button has been replaced on a picking kanban view-->
    <t t-extend="KanbanView.buttons">
        <t t-if="widget.modelName=='stock.picking'" t-jquery="button.o_list_button_add_planned" t-operation="after">
           <t t-call="ImportView.import_button"/>
        </t>
    </t>

</templates>